wiredify/__init__.py
wiredify/main.py
wiredify/py.typed
wiredify-0.1.0.dist-info/LICENSE.txt
wiredify-0.1.0.dist-info/METADATA
wiredify-0.1.0.dist-info/WHEEL
wiredify-0.1.0.dist-info/entry_points.txt
wiredify-0.1.0.dist-info/RECORD
