Metadata-Version: 2.1
Name: wiredify
Version: 0.1.0
Summary: Convert japanese kana from ba-bi-bu-be-bo into va-vi-vu-ve-vo
Home-page: https://github.com/eggplants/wiredify
License: MIT
Keywords: joke,cli,japanese
Author: eggplants
Author-email: w10776e8w@yahoo.co.jp
Requires-Python: >=3.8,<4
Classifier: License :: OSI Approved :: MIT License
Classifier: Programming Language :: Python
Classifier: Programming Language :: Python :: 3
Classifier: Programming Language :: Python :: 3.8
Classifier: Programming Language :: Python :: 3.9
Classifier: Programming Language :: Python :: 3.10
Classifier: Programming Language :: Python :: 3.11
Classifier: Programming Language :: Python :: 3.12
Classifier: Programming Language :: Python :: 3 :: Only
Classifier: Programming Language :: Python :: Implementation :: CPython
Project-URL: Repository, https://github.com/eggplants/wiredify
